[
    {
        "id": "CnB5Rt9mEBTwSI",
        "reason": "Generic Filter"
    },
    {
        "id": "8de2880669ff167e",
        "reason": "Generic Filter"
    },
    {
        "id": "Kill_bot",
        "reason": "horrendous bot"
    },
    {
        "id": ["BOT***(3)***", "BOT***(2)***"],
        "reason": "spammy spammer spam bot"
    },
    {
        "id": "Gam3rArthr",
        "reason": "bud is NOT an admin gng"
    },
    {
        "id": "Dream",
        "reason": "make scripted manhunts somewhere else gng"
    }
]